{
  "type": "FeatureCollection",
  "features": [
    {
      "type": "Feature",
      "geometry": {
        "type": "Point",
        "coordinates": [-104.9964, 39.7545]
      },
      "properties": {
        "name": "The True Life Compaies (Corp)",
        "description": "1601 19th Street, Suite 550 <br>Denver, CO 80202"
      }
    }
  ]
}
